tau/__init__.py
tau/partition.py
tau/tau.py
tau_graph_clustering-1.0.1.dist-info/LICENCE
tau_graph_clustering-1.0.1.dist-info/METADATA
tau_graph_clustering-1.0.1.dist-info/WHEEL
tau_graph_clustering-1.0.1.dist-info/top_level.txt
tau_graph_clustering-1.0.1.dist-info/RECORD
