Metadata-Version: 2.1
Name: tau-graph-clustering
Version: 1.0.1
Summary: TAU is a genetic algorithm for graph clustering.
Project-URL: Repository, https://github.com/aberdichevskaia/pyTAU
Classifier: Programming Language :: Python :: 3
Classifier: Operating System :: OS Independent
Requires-Python: >=3.8
License-File: LICENCE
Requires-Dist: numpy >=1.14.0
Requires-Dist: igraph >=0.9.8
Requires-Dist: scikit-learn >=0.24.0
